cloudferry/__init__.py
cloudferry/cfglib.py
cloudferry/config.py
cloudferry/data_storage.py
cloudferry/discover.py
cloudferry/actions/__init__.py
cloudferry/actions/identity/__init__.py
cloudferry/actions/identity/identity_transporter.py
cloudferry/actions/block_storage/__init__.py
cloudferry/actions/block_storage/attach_used_volumes_via_compute.py
cloudferry/actions/block_storage/detach_used_volumes_via_compute.py
cloudferry/actions/block_storage/get_info_volumes.py
cloudferry/actions/block_storage/migrate_volumes.py
cloudferry/actions/block_storage/set_volume_id.py
cloudferry/actions/block_storage/transport_storage_resources.py
cloudferry/actions/live_migration/__init__.py
cloudferry/actions/live_migration/live_migration.py
cloudferry/actions/filter/__init__.py
cloudferry/actions/filter/filter_similar_vms_from_dst.py
cloudferry/actions/filter/get_filter.py
cloudferry/actions/helper/__init__.py
cloudferry/actions/helper/failure_act.py
cloudferry/actions/helper/fake_action.py
cloudferry/actions/helper/remove_bbcp.py
cloudferry/actions/helper/sleep.py
cloudferry/actions/helper/task_transfer.py
cloudferry/actions/networking/__init__.py
cloudferry/actions/networking/instance_floatingip_actions.py
cloudferry/actions/networking/networks_transporter.py
cloudferry/actions/networking/prepare_networks.py
cloudferry/actions/prechecks/__init__.py
cloudferry/actions/prechecks/check_affinity.py
cloudferry/actions/prechecks/check_bandwidth.py
cloudferry/actions/prechecks/check_cloud.py
cloudferry/actions/prechecks/check_config_quota_neutron.py
cloudferry/actions/prechecks/check_copy_engine_configuration.py
cloudferry/actions/prechecks/check_filter.py
cloudferry/actions/prechecks/check_instances.py
cloudferry/actions/prechecks/check_networks.py
cloudferry/actions/prechecks/check_openstack_apis.py
cloudferry/actions/prechecks/check_quotas.py
cloudferry/actions/prechecks/check_rabbitmq.py
cloudferry/actions/prechecks/check_sql.py
CloudFerry-1.55.2.dist-info/top_level.txt
CloudFerry-1.55.2.dist-info/entry_points.txt
CloudFerry-1.55.2.dist-info/pbr.json
CloudFerry-1.55.2.dist-info/METADATA
CloudFerry-1.55.2.dist-info/DESCRIPTION.rst
CloudFerry-1.55.2.dist-info/metadata.json
CloudFerry-1.55.2.dist-info/WHEEL
CloudFerry-1.55.2.dist-info/RECORD
