Metadata-Version: 2.0
Name: CloudFerry
Version: 1.55.2
Summary: Openstack cloud workload migration tool
Home-page: https://github.com/Mirantis/CloudFerry
Author: Mirantis Inc.
Author-email: workloadmobility@mirantis.com
License: Apache-2
Platform: UNKNOWN
Classifier: Development Status :: 4 - Beta
Classifier: Environment :: Console
Classifier: Environment :: OpenStack
Classifier: Intended Audience :: Developers
Classifier: Intended Audience :: Information Technology
Classifier: License :: OSI Approved :: Apache Software License
Classifier: Operating System :: OS Independent
Classifier: Programming Language :: Python
Requires-Dist: colorlog (==2.6.1)
Requires-Dist: fabric (==1.10.2)
Requires-Dist: ipaddr (==2.1.11)
Requires-Dist: PyMySQL (==0.6.7)
Requires-Dist: oslo.config (==3.9.0)
Requires-Dist: oslo.utils (==3.15.0)
Requires-Dist: pika (==0.9.14)
Requires-Dist: pycrypto (==2.6.1)
Requires-Dist: python-cinderclient (==1.3.1)
Requires-Dist: python-glanceclient (==1.1.0)
Requires-Dist: python-keystoneclient (==1.6.0)
Requires-Dist: python-neutronclient (==2.6.0)
Requires-Dist: python-novaclient (==2.25.0)
Requires-Dist: python-swiftclient (==2.3.1)
Requires-Dist: pyyaml (==3.11)
Requires-Dist: pywbem (==0.7.0)
Requires-Dist: redis (==2.10.5)
Requires-Dist: sqlalchemy (==1.0.12)
Requires-Dist: marshmallow (==2.4.2)
Requires-Dist: jmespath (==0.9.0)
Requires-Dist: pyOpenSSL (==16.2.0)
Requires-Dist: paramiko (==1.16.0)
Requires-Dist: taskflow (==1.30.0)
Requires-Dist: alembic (==0.8.5)
Requires-Dist: SQLAlchemy-Utils (==0.32.1)
Requires-Dist: cliff (==2.0.0)
Requires-Dist: oslo.serialization (==2.7.0)
